tokdu/__init__.py
tokdu/config.py
tokdu/tokdu.py
tokdu-0.1.5.dist-info/licenses/LICENSE
tokdu-0.1.5.dist-info/METADATA
tokdu-0.1.5.dist-info/WHEEL
tokdu-0.1.5.dist-info/entry_points.txt
tokdu-0.1.5.dist-info/top_level.txt
tokdu-0.1.5.dist-info/RECORD
