Metadata-Version: 2.4
Name: tokdu
Version: 0.1.5
Summary: A token counting TUI tool that respects .gitignore and skips binary files
Author-email: Halil Tezcan KARABULUT <unitythemaker@gmail.com>
License: MIT
Project-URL: Homepage, https://github.com/unitythemaker/tokdu
Classifier: Programming Language :: Python :: 3
Classifier: Operating System :: OS Independent
Requires-Python: >=3.6
License-File: LICENSE
Requires-Dist: tiktoken==0.9.0
Requires-Dist: pathspec==0.12.1
Requires-Dist: appdirs>=1.4.4
Provides-Extra: gemini
Requires-Dist: google-cloud-aiplatform[tokenization]>=1.57.0; extra == "gemini"
Provides-Extra: anthropic
Requires-Dist: anthropic>=0.49.0; extra == "anthropic"
Dynamic: license-file
